CHANGELOG.md
README.md
mitol/__init__.py
mitol/hubspot_api/__init__.py
mitol/hubspot_api/admin.py
mitol/hubspot_api/api.py
mitol/hubspot_api/apps.py
mitol/hubspot_api/decorators.py
mitol/hubspot_api/exceptions.py
mitol/hubspot_api/factories.py
mitol/hubspot_api/models.py
mitol/hubspot_api/py.typed
mitol/hubspot_api/migrations/0001_initial.py
mitol/hubspot_api/migrations/__init__.py
mitol/hubspot_api/settings/hubspot_api.py
mitol_django_hubspot_api-2025.12.18.dist-info/METADATA
mitol_django_hubspot_api-2025.12.18.dist-info/WHEEL
mitol_django_hubspot_api-2025.12.18.dist-info/RECORD
