Metadata-Version: 2.4
Name: mitol-django-hubspot-api
Version: 2025.12.18
Summary: Django application for Hubspot API integration
License-Expression: BSD-3-Clause
Requires-Python: >=3.10
Requires-Dist: django-stubs>=1.13.1
Requires-Dist: django>=3.0
Requires-Dist: djangorestframework>=3.0.0
Requires-Dist: factory-boy~=3.2
Requires-Dist: hubspot-api-client==12.0.0
Requires-Dist: mitol-django-common
Requires-Dist: requests>=2.20.0
Requires-Dist: urllib3>=1.26.5
